setup.cfg
setup.py
ytdata/__init__.py
ytdata/cli.py
ytdata/example.py
ytdata/ytdata.py
ytdata.egg-info/PKG-INFO
ytdata.egg-info/SOURCES.txt
ytdata.egg-info/dependency_links.txt
ytdata.egg-info/entry_points.txt
ytdata.egg-info/not-zip-safe
ytdata.egg-info/requires.txt
ytdata.egg-info/top_level.txt