Metadata-Version: 1.1
Name: ytdata
Version: 0.1.0
Summary: Obtain video details for YouTube channels.
Home-page: https://github.com/danlou/ytdata
Author: Daniel Loureiro
Author-email: daniel.b.loureiro@gmail.com
License: MIT
Platform: any
Classifier: Development Status :: 4 - Beta
Classifier: Environment :: Console
Classifier: Intended Audience :: Developers
Classifier: License :: OSI Approved :: MIT License
Classifier: Operating System :: MacOS
Classifier: Operating System :: Unix
Classifier: Programming Language :: Python
Classifier: Programming Language :: Python :: 3
Classifier: Topic :: Software Development :: Libraries :: Python Modules
